{
  "schemaVersion": 1,
  "id": "oreharvest",
  "version": "1.0.3",
  "name": "Ore Harvest",
  "description": "A minecraft mod that allow you growth ore crops",
  "authors": [
    "HinL"
  ],
  "contact": {
    "sources": "https://github.com/hinls1007/OreHarvest"
  },
  "license": "MIT",
  "icon": "assets/oreharvest/mod_icon.png",
  "environment": "*",
  "entrypoints": {
    "main": [
      {
        "adapter": "kotlin",
        "value": "app.hinl.oreharvest.OreHarvest"
      }
    ],
    "client": [
      {
        "adapter": "kotlin",
        "value": "app.hinl.oreharvest.OreHarvestClient"
      }
    ]
  },
  "mixins": [
  ],
  "depends": {
    "fabricloader": ">=0.14.8",
    "fabric": "*",
    "fabric-language-kotlin": ">=1.8.2+kotlin.1.7.10",
    "minecraft": "1.19.x",
    "java": ">=17"
  }
}
